keepthis/KeepThis.py
keepthis/MemcachedConnection.py
keepthis/__init__.py
keepthis/exceptions.py
keepthis-0.0.4.dist-info/LICENSE
keepthis-0.0.4.dist-info/METADATA
keepthis-0.0.4.dist-info/WHEEL
keepthis-0.0.4.dist-info/top_level.txt
keepthis-0.0.4.dist-info/RECORD
