Metadata-Version: 2.1
Name: keepthis
Version: 0.0.4
Summary: KeepThis - helper tool for Data Scientists collaborative work. Cache artifacts and share them with your teammates.
Home-page: https://github.com/puhoshville/keep-this
Author: Dmitrii Pukhov
Author-email: pukhovdn@yandex.ru
License: MIT
Platform: UNKNOWN
Classifier: Programming Language :: Python :: 3
Classifier: License :: OSI Approved :: MIT License
Classifier: Operating System :: OS Independent
Requires-Python: >=3.5
